{
  "id": 374,
  "cnpj": "60.500.139/0001-26",
  "name": "SARAIVA LIVREIROS S.A. - EM RECUPERAÇÃO JUDICIAL",
  "tickers": [
    "SLED3",
    "SLED4"
  ],
  "shortTicker": "SLED",
  "revenue": {
    "accountCode": "3.01",
    "accountDescripton": "Receita de Venda de Bens e/ou Serviços",
    "data": {
      "2009": {
        "version": 1,
        "value": 1248353
      },
      "2010": {
        "version": 1,
        "value": 1564936
      },
      "2011": {
        "version": 1,
        "value": 1888967
      },
      "2012": {
        "version": 1,
        "value": 1923585
      },
      "2013": {
        "version": 1,
        "value": 2143751
      },
      "2014": {
        "version": 1,
        "value": 2275315
      },
      "2015": {
        "version": 1,
        "value": 1772815
      },
      "2016": {
        "version": 1,
        "value": 1737563
      },
      "2017": {
        "version": 1,
        "value": 1724886
      },
      "2018": {
        "version": 1,
        "value": 1445422
      },
      "2019": {
        "version": 1,
        "value": 669658
      },
      "2020": {
        "version": 1,
        "value": 246325
      }
    }
  },
  "financialResult": {
    "accountCode": "3.06",
    "accountDescripton": "Resultado Financeiro",
    "data": {
      "2009": {
        "version": 1,
        "value": -20548
      },
      "2010": {
        "version": 1,
        "value": -32726
      },
      "2011": {
        "version": 1,
        "value": -49933
      },
      "2012": {
        "version": 1,
        "value": -38138
      },
      "2013": {
        "version": 1,
        "value": -38875
      },
      "2014": {
        "version": 1,
        "value": -70012
      },
      "2015": {
        "version": 1,
        "value": -80478
      },
      "2016": {
        "version": 1,
        "value": -53647
      },
      "2017": {
        "version": 1,
        "value": -48372
      },
      "2018": {
        "version": 1,
        "value": -50342
      },
      "2019": {
        "version": 1,
        "value": 230076
      },
      "2020": {
        "version": 1,
        "value": -29694
      }
    }
  },
  "profit": {
    "accountCode": "3.11",
    "accountDescripton": "Lucro/Prejuízo Consolidado do Período",
    "data": {
      "2009": {
        "version": 1,
        "value": 51478
      },
      "2010": {
        "version": 1,
        "value": 61023
      },
      "2011": {
        "version": 1,
        "value": 64921
      },
      "2012": {
        "version": 1,
        "value": 77015
      },
      "2013": {
        "version": 1,
        "value": 13021
      },
      "2014": {
        "version": 1,
        "value": 5747
      },
      "2015": {
        "version": 1,
        "value": 93714
      },
      "2016": {
        "version": 1,
        "value": -49823
      },
      "2017": {
        "version": 1,
        "value": -52012
      },
      "2018": {
        "version": 1,
        "value": -301754
      },
      "2019": {
        "version": 1,
        "value": -318072
      },
      "2020": {
        "version": 1,
        "value": -419628
      }
    }
  }
}