{
  "id": 412,
  "cnpj": "73.178.600/0001-18",
  "name": "CYRELA BRAZIL REALTY S.A.EMPREEND E PART",
  "tickers": [
    "CYRE3"
  ],
  "shortTicker": "CYRE",
  "revenue": {
    "accountCode": "3.01",
    "accountDescripton": "Receita de Venda de Bens e/ou Serviços",
    "data": {
      "2009": {
        "version": 2,
        "value": 4087825
      },
      "2010": {
        "version": 2,
        "value": 4890105
      },
      "2011": {
        "version": 1,
        "value": 6126781
      },
      "2012": {
        "version": 1,
        "value": 5837953
      },
      "2013": {
        "version": 1,
        "value": 5371882
      },
      "2014": {
        "version": 2,
        "value": 5817927
      },
      "2015": {
        "version": 2,
        "value": 4341184
      },
      "2016": {
        "version": 1,
        "value": 3195310
      },
      "2017": {
        "version": 2,
        "value": 2673770
      },
      "2018": {
        "version": 2,
        "value": 3146157
      },
      "2019": {
        "version": 1,
        "value": 3930822
      }
    }
  },
  "financialResult": {
    "accountCode": "3.06",
    "accountDescripton": "Resultado Financeiro",
    "data": {
      "2009": {
        "version": 2,
        "value": -14533
      },
      "2010": {
        "version": 2,
        "value": 65232
      },
      "2011": {
        "version": 1,
        "value": 49619
      },
      "2012": {
        "version": 1,
        "value": 18155
      },
      "2013": {
        "version": 1,
        "value": 27878
      },
      "2014": {
        "version": 2,
        "value": 16144
      },
      "2015": {
        "version": 2,
        "value": 17597
      },
      "2016": {
        "version": 1,
        "value": 79143
      },
      "2017": {
        "version": 2,
        "value": 37812
      },
      "2018": {
        "version": 2,
        "value": 22118
      },
      "2019": {
        "version": 1,
        "value": 30593
      }
    }
  },
  "profit": {
    "accountCode": "3.11",
    "accountDescripton": "Lucro/Prejuízo Consolidado do Período",
    "data": {
      "2009": {
        "version": 2,
        "value": 826898
      },
      "2010": {
        "version": 2,
        "value": 685066
      },
      "2011": {
        "version": 1,
        "value": 592186
      },
      "2012": {
        "version": 1,
        "value": 778719
      },
      "2013": {
        "version": 1,
        "value": 893999
      },
      "2014": {
        "version": 2,
        "value": 831386
      },
      "2015": {
        "version": 2,
        "value": 593153
      },
      "2016": {
        "version": 1,
        "value": 244620
      },
      "2017": {
        "version": 2,
        "value": -10539
      },
      "2018": {
        "version": 2,
        "value": 6028
      },
      "2019": {
        "version": 1,
        "value": 534316
      }
    }
  }
}