{
  "id": 594,
  "cnpj": "02.808.708/0001-07",
  "name": "COMPANHIA DE BEBIDAS DAS AMÉRICAS-AMBEV",
  "revenue": {
    "accountCode": "3.01",
    "accountDescripton": "Receita de Venda de Bens e/ou Serviços",
    "data": {
      "2009": {
        "version": 1,
        "value": 23194048
      },
      "2010": {
        "version": 1,
        "value": 25233310
      },
      "2011": {
        "version": 1,
        "value": 27126719
      },
      "2012": {
        "version": 1,
        "value": 32231027
      }
    }
  },
  "financialResult": {
    "accountCode": "3.06",
    "accountDescripton": "Resultado Financeiro",
    "data": {
      "2009": {
        "version": 1,
        "value": -982093
      },
      "2010": {
        "version": 1,
        "value": -319411
      },
      "2011": {
        "version": 1,
        "value": -468164
      },
      "2012": {
        "version": 1,
        "value": -812814
      }
    }
  },
  "profit": {
    "accountCode": "3.11",
    "accountDescripton": "Lucro/Prejuízo Consolidado do Período",
    "data": {
      "2009": {
        "version": 1,
        "value": 5988345
      },
      "2010": {
        "version": 1,
        "value": 7619243
      },
      "2011": {
        "version": 1,
        "value": 8719764
      },
      "2012": {
        "version": 1,
        "value": 10642555
      }
    }
  }
}