{
  "id": 648,
  "cnpj": "10.753.164/0001-43",
  "name": "ECO SECURITIZADORA DIREITOS CRED AGRONEGÓCIO S.A.",
  "revenue": {
    "accountCode": "3.01",
    "accountDescripton": "Receita de Venda de Bens e/ou Serviços",
    "data": {
      "2009": {
        "version": 1,
        "value": 1217
      },
      "2010": {
        "version": 1,
        "value": 1560
      }
    }
  },
  "financialResult": {
    "accountCode": "3.06",
    "accountDescripton": "Resultado Financeiro",
    "data": {
      "2009": {
        "version": 1,
        "value": -2
      },
      "2010": {
        "version": 1,
        "value": -3
      }
    }
  },
  "profit": {
    "accountCode": "3.11",
    "accountDescripton": "Lucro/Prejuízo Consolidado do Período",
    "data": {
      "2009": {
        "version": 1,
        "value": 555
      },
      "2010": {
        "version": 1,
        "value": -870
      }
    }
  }
}